trc_cli/__init__.py
trc_cli/authenticator.py
trc_cli/constants.py
trc_cli/demo_factory.py
trc_cli/exceptions.py
trc_cli/main.py
trc_cli/provisioner.py
trc_cli/run.py
trc_cli/static/microservices.json
trc_cli/static/sboms/c#.json
trc_cli/static/sboms/go.json
trc_cli/static/sboms/python.json
trc_cli/static/sboms/python_2.json
trc_cli/static/sboms/sbom.json
trc_cli/static/sboms/ts.json
trc_cli/static/sboms/ts_2.json
trc_cli/static/sboms/ts_3.json
trc_cli/utils.py
trc_cli-0.2.5.dist-info/METADATA
trc_cli-0.2.5.dist-info/WHEEL
trc_cli-0.2.5.dist-info/entry_points.txt
trc_cli-0.2.5.dist-info/RECORD
